[
	{
		"points": [
			[
				320,
				5
			],
			[
				171,
				85
			],
			[
				177,
				7
			],
			[
				170,
				71
			],
			[
				223,
				-26
			],
			[
				169,
				-25
			],
			[
				315,
				89
			],
			[
				244,
				62
			],
			[
				183,
				-31
			],
			[
				206,
				-52
			]
		],
		"cost": 0.426494
	},
	{
		"points": [
			[
				33,
				-52
			],
			[
				239,
				6
			],
			[
				210,
				-44
			],
			[
				303,
				1
			],
			[
				121,
				31
			],
			[
				118,
				62
			],
			[
				10,
				-15
			],
			[
				296,
				-9
			],
			[
				272,
				2
			],
			[
				230,
				-54
			]
		],
		"cost": 0.448209
	},
	{
		"points": [
			[
				7,
				62
			],
			[
				154,
				-76
			],
			[
				18,
				-56
			],
			[
				39,
				-23
			],
			[
				317,
				36
			],
			[
				151,
				83
			],
			[
				105,
				68
			],
			[
				173,
				-60
			],
			[
				220,
				-11
			],
			[
				54,
				61
			]
		],
		"cost": 0.426398
	},
	{
		"points": [
			[
				44,
				-5
			],
			[
				340,
				-60
			],
			[
				58,
				60
			],
			[
				53,
				86
			],
			[
				310,
				47
			],
			[
				218,
				35
			],
			[
				243,
				77
			],
			[
				28,
				74
			],
			[
				352,
				-54
			],
			[
				38,
				14
			]
		],
		"cost": 0.357442
	},
	{
		"points": [
			[
				285,
				-53
			],
			[
				83,
				70
			],
			[
				192,
				-87
			],
			[
				23,
				-62
			],
			[
				340,
				-70
			],
			[
				164,
				-80
			],
			[
				217,
				-74
			],
			[
				131,
				-62
			],
			[
				73,
				-10
			],
			[
				340,
				41
			]
		],
		"cost": 0.397188
	},
	{
		"points": [
			[
				211,
				40
			],
			[
				162,
				-5
			],
			[
				271,
				38
			],
			[
				302,
				-59
			],
			[
				328,
				-87
			],
			[
				245,
				-68
			],
			[
				218,
				35
			],
			[
				335,
				72
			],
			[
				80,
				38
			],
			[
				118,
				-72
			]
		],
		"cost": 0.439929
	},
	{
		"points": [
			[
				228,
				33
			],
			[
				169,
				-84
			],
			[
				20,
				47
			],
			[
				280,
				83
			],
			[
				93,
				58
			],
			[
				194,
				76
			],
			[
				295,
				25
			],
			[
				191,
				0
			],
			[
				97,
				-35
			],
			[
				282,
				75
			]
		],
		"cost": 0.464377
	},
	{
		"points": [
			[
				67,
				-85
			],
			[
				357,
				-54
			],
			[
				39,
				-2
			],
			[
				33,
				78
			],
			[
				59,
				83
			],
			[
				160,
				32
			],
			[
				250,
				-53
			],
			[
				248,
				-26
			],
			[
				46,
				-83
			],
			[
				349,
				-71
			]
		],
		"cost": 0.272457
	},
	{
		"points": [
			[
				7,
				30
			],
			[
				6,
				82
			],
			[
				62,
				-5
			],
			[
				18,
				-57
			],
			[
				252,
				-88
			],
			[
				225,
				85
			],
			[
				106,
				42
			],
			[
				211,
				0
			],
			[
				332,
				-46
			],
			[
				302,
				28
			]
		],
		"cost": 0.4499
	},
	{
		"points": [
			[
				55,
				-29
			],
			[
				298,
				-59
			],
			[
				224,
				27
			],
			[
				272,
				0
			],
			[
				243,
				-34
			],
			[
				264,
				-42
			],
			[
				185,
				-42
			],
			[
				150,
				-35
			],
			[
				313,
				62
			],
			[
				47,
				-16
			]
		],
		"cost": 0.363671
	}
]