[
	{
		"points": [
			[
				105,
				64
			],
			[
				174,
				81
			],
			[
				277,
				63
			],
			[
				198,
				-48
			],
			[
				248,
				-70
			],
			[
				310,
				-69
			],
			[
				93,
				-65
			],
			[
				73,
				57
			]
		],
		"cost": 0.232289,
		"time": 0.024439
	},
	{
		"points": [
			[
				202,
				35
			],
			[
				236,
				-1
			],
			[
				216,
				-4
			],
			[
				95,
				-74
			],
			[
				311,
				-58
			],
			[
				318,
				46
			],
			[
				9,
				64
			],
			[
				352,
				75
			]
		],
		"cost": 0.236763,
		"time": 0.021108
	},
	{
		"points": [
			[
				138,
				-29
			],
			[
				58,
				-57
			],
			[
				54,
				-35
			],
			[
				22,
				-49
			],
			[
				339,
				-55
			],
			[
				295,
				-13
			],
			[
				217,
				0
			],
			[
				225,
				-49
			]
		],
		"cost": 0.214132,
		"time": 0.021044
	},
	{
		"points": [
			[
				114,
				-31
			],
			[
				115,
				-35
			],
			[
				85,
				-31
			],
			[
				264,
				-45
			],
			[
				294,
				16
			],
			[
				317,
				26
			],
			[
				156,
				76
			],
			[
				109,
				-22
			]
		],
		"cost": 0.229673,
		"time": 0.018417
	},
	{
		"points": [
			[
				137,
				-48
			],
			[
				48,
				-36
			],
			[
				92,
				-9
			],
			[
				141,
				39
			],
			[
				298,
				80
			],
			[
				345,
				51
			],
			[
				325,
				-44
			],
			[
				175,
				-87
			]
		],
		"cost": 0.253227,
		"time": 0.020742
	},
	{
		"points": [
			[
				163,
				-8
			],
			[
				166,
				-73
			],
			[
				148,
				-62
			],
			[
				126,
				-36
			],
			[
				170,
				88
			],
			[
				328,
				68
			],
			[
				252,
				79
			],
			[
				204,
				42
			]
		],
		"cost": 0.211888,
		"time": 0.021352
	},
	{
		"points": [
			[
				57,
				38
			],
			[
				2,
				-78
			],
			[
				296,
				-74
			],
			[
				211,
				-2
			],
			[
				262,
				53
			],
			[
				165,
				31
			],
			[
				149,
				5
			],
			[
				89,
				18
			]
		],
		"cost": 0.270091,
		"time": 0.022582
	},
	{
		"points": [
			[
				31,
				-42
			],
			[
				93,
				-61
			],
			[
				134,
				38
			],
			[
				131,
				64
			],
			[
				183,
				85
			],
			[
				259,
				80
			],
			[
				307,
				75
			],
			[
				59,
				54
			]
		],
		"cost": 0.199145,
		"time": 0.0233
	},
	{
		"points": [
			[
				57,
				-46
			],
			[
				96,
				49
			],
			[
				117,
				67
			],
			[
				3,
				-24
			],
			[
				262,
				-54
			],
			[
				303,
				-88
			],
			[
				118,
				-88
			],
			[
				112,
				-74
			]
		],
		"cost": 0.227378,
		"time": 0.022509
	},
	{
		"points": [
			[
				193,
				-67
			],
			[
				164,
				-39
			],
			[
				269,
				76
			],
			[
				340,
				81
			],
			[
				20,
				76
			],
			[
				77,
				65
			],
			[
				82,
				13
			],
			[
				221,
				-75
			]
		],
		"cost": 0.214153,
		"time": 0.02241
	},
	{
		"points": [
			[
				19,
				-36
			],
			[
				301,
				-66
			],
			[
				229,
				-45
			],
			[
				123,
				-37
			],
			[
				167,
				-8
			],
			[
				134,
				21
			],
			[
				93,
				9
			],
			[
				355,
				50
			]
		],
		"cost": 0.266975,
		"time": 0.020772
	},
	{
		"points": [
			[
				234,
				89
			],
			[
				56,
				56
			],
			[
				113,
				60
			],
			[
				135,
				-56
			],
			[
				124,
				-72
			],
			[
				307,
				-7
			],
			[
				244,
				78
			],
			[
				209,
				74
			]
		],
		"cost": 0.230655,
		"time": 0.022831
	},
	{
		"points": [
			[
				164,
				86
			],
			[
				311,
				-18
			],
			[
				268,
				-73
			],
			[
				220,
				-70
			],
			[
				175,
				-50
			],
			[
				194,
				-48
			],
			[
				229,
				-39
			],
			[
				201,
				74
			]
		],
		"cost": 0.21237,
		"time": 0.021959
	},
	{
		"points": [
			[
				268,
				-65
			],
			[
				262,
				-35
			],
			[
				286,
				32
			],
			[
				86,
				80
			],
			[
				25,
				53
			],
			[
				28,
				34
			],
			[
				32,
				-19
			],
			[
				29,
				-83
			]
		],
		"cost": 0.203872,
		"time": 0.022507
	},
	{
		"points": [
			[
				266,
				47
			],
			[
				236,
				-14
			],
			[
				236,
				-84
			],
			[
				81,
				-89
			],
			[
				210,
				-19
			],
			[
				152,
				77
			],
			[
				14,
				79
			],
			[
				335,
				72
			]
		],
		"cost": 0.217004,
		"time": 0.02213
	},
	{
		"points": [
			[
				255,
				-40
			],
			[
				243,
				-84
			],
			[
				338,
				-56
			],
			[
				34,
				-67
			],
			[
				78,
				-7
			],
			[
				40,
				43
			],
			[
				76,
				76
			],
			[
				267,
				-22
			]
		],
		"cost": 0.23185,
		"time": 0.021464
	},
	{
		"points": [
			[
				144,
				51
			],
			[
				170,
				79
			],
			[
				250,
				12
			],
			[
				293,
				13
			],
			[
				298,
				-63
			],
			[
				92,
				-65
			],
			[
				113,
				-69
			],
			[
				187,
				5
			]
		],
		"cost": 0.239292,
		"time": 0.021766
	},
	{
		"points": [
			[
				72,
				31
			],
			[
				134,
				26
			],
			[
				170,
				60
			],
			[
				204,
				-29
			],
			[
				18,
				-70
			],
			[
				310,
				7
			],
			[
				346,
				56
			],
			[
				11,
				64
			]
		],
		"cost": 0.267018,
		"time": 0.021512
	},
	{
		"points": [
			[
				28,
				11
			],
			[
				52,
				-88
			],
			[
				117,
				-39
			],
			[
				160,
				26
			],
			[
				159,
				49
			],
			[
				329,
				89
			],
			[
				82,
				65
			],
			[
				58,
				45
			]
		],
		"cost": 0.212625,
		"time": 0.02148
	},
	{
		"points": [
			[
				210,
				16
			],
			[
				247,
				-17
			],
			[
				278,
				-65
			],
			[
				111,
				-55
			],
			[
				28,
				-23
			],
			[
				0,
				-7
			],
			[
				212,
				59
			],
			[
				200,
				47
			]
		],
		"cost": 0.237994,
		"time": 0.020879
	},
	{
		"points": [
			[
				102,
				-29
			],
			[
				162,
				-42
			],
			[
				150,
				47
			],
			[
				230,
				46
			],
			[
				261,
				57
			],
			[
				293,
				72
			],
			[
				324,
				75
			],
			[
				57,
				8
			]
		],
		"cost": 0.21261,
		"time": 0.021678
	},
	{
		"points": [
			[
				94,
				35
			],
			[
				0,
				14
			],
			[
				283,
				-50
			],
			[
				255,
				-60
			],
			[
				84,
				-80
			],
			[
				20,
				-72
			],
			[
				2,
				-69
			],
			[
				16,
				-51
			]
		],
		"cost": 0.215732,
		"time": 0.021571
	},
	{
		"points": [
			[
				294,
				17
			],
			[
				255,
				56
			],
			[
				359,
				86
			],
			[
				57,
				67
			],
			[
				150,
				48
			],
			[
				159,
				7
			],
			[
				189,
				-84
			],
			[
				289,
				-69
			]
		],
		"cost": 0.219678,
		"time": 0.023034
	},
	{
		"points": [
			[
				193,
				80
			],
			[
				216,
				60
			],
			[
				189,
				17
			],
			[
				210,
				0
			],
			[
				41,
				-17
			],
			[
				31,
				11
			],
			[
				344,
				86
			],
			[
				107,
				80
			]
		],
		"cost": 0.215093,
		"time": 0.022808
	},
	{
		"points": [
			[
				200,
				0
			],
			[
				150,
				-11
			],
			[
				169,
				8
			],
			[
				182,
				76
			],
			[
				79,
				64
			],
			[
				31,
				33
			],
			[
				309,
				-30
			],
			[
				274,
				24
			]
		],
		"cost": 0.25531,
		"time": 0.020369
	},
	{
		"points": [
			[
				86,
				63
			],
			[
				24,
				38
			],
			[
				75,
				33
			],
			[
				115,
				7
			],
			[
				123,
				-28
			],
			[
				196,
				-22
			],
			[
				221,
				84
			],
			[
				305,
				75
			]
		],
		"cost": 0.218821,
		"time": 0.0207
	},
	{
		"points": [
			[
				135,
				1
			],
			[
				243,
				-47
			],
			[
				224,
				-15
			],
			[
				201,
				-1
			],
			[
				210,
				8
			],
			[
				222,
				53
			],
			[
				282,
				62
			],
			[
				161,
				52
			]
		],
		"cost": 0.204733,
		"time": 0.021146
	},
	{
		"points": [
			[
				8,
				-57
			],
			[
				212,
				-26
			],
			[
				189,
				-4
			],
			[
				152,
				13
			],
			[
				204,
				53
			],
			[
				33,
				73
			],
			[
				294,
				60
			],
			[
				336,
				23
			]
		],
		"cost": 0.24733,
		"time": 0.023328
	},
	{
		"points": [
			[
				32,
				22
			],
			[
				27,
				-15
			],
			[
				152,
				-82
			],
			[
				243,
				-21
			],
			[
				204,
				33
			],
			[
				266,
				50
			],
			[
				209,
				89
			],
			[
				40,
				77
			]
		],
		"cost": 0.22691,
		"time": 0.02103
	},
	{
		"points": [
			[
				217,
				-78
			],
			[
				323,
				-26
			],
			[
				279,
				-36
			],
			[
				261,
				7
			],
			[
				273,
				71
			],
			[
				49,
				47
			],
			[
				95,
				23
			],
			[
				202,
				-6
			]
		],
		"cost": 0.277345,
		"time": 0.020861
	},
	{
		"points": [
			[
				98,
				-38
			],
			[
				154,
				52
			],
			[
				137,
				65
			],
			[
				52,
				86
			],
			[
				332,
				25
			],
			[
				18,
				-29
			],
			[
				352,
				-43
			],
			[
				311,
				-87
			]
		],
		"cost": 0.223044,
		"time": 0.02212
	},
	{
		"points": [
			[
				203,
				72
			],
			[
				249,
				18
			],
			[
				210,
				-12
			],
			[
				286,
				-47
			],
			[
				141,
				-87
			],
			[
				9,
				-11
			],
			[
				57,
				17
			],
			[
				131,
				11
			]
		],
		"cost": 0.282188,
		"time": 0.020965
	},
	{
		"points": [
			[
				4,
				-3
			],
			[
				74,
				-19
			],
			[
				240,
				-49
			],
			[
				250,
				25
			],
			[
				219,
				56
			],
			[
				316,
				60
			],
			[
				90,
				79
			],
			[
				44,
				47
			]
		],
		"cost": 0.264568,
		"time": 0.02252
	},
	{
		"points": [
			[
				158,
				59
			],
			[
				55,
				-10
			],
			[
				117,
				-13
			],
			[
				157,
				10
			],
			[
				189,
				-4
			],
			[
				225,
				-7
			],
			[
				229,
				2
			],
			[
				240,
				61
			]
		],
		"cost": 0.216866,
		"time": 0.019985
	},
	{
		"points": [
			[
				114,
				21
			],
			[
				277,
				83
			],
			[
				27,
				66
			],
			[
				359,
				17
			],
			[
				296,
				-30
			],
			[
				178,
				-79
			],
			[
				129,
				-41
			],
			[
				194,
				-1
			]
		],
		"cost": 0.273156,
		"time": 0.021741
	},
	{
		"points": [
			[
				39,
				35
			],
			[
				59,
				53
			],
			[
				96,
				22
			],
			[
				210,
				68
			],
			[
				196,
				-25
			],
			[
				228,
				-9
			],
			[
				272,
				14
			],
			[
				327,
				-21
			]
		],
		"cost": 0.262633,
		"time": 0.021521
	},
	{
		"points": [
			[
				159,
				49
			],
			[
				155,
				58
			],
			[
				249,
				49
			],
			[
				308,
				84
			],
			[
				354,
				59
			],
			[
				43,
				-63
			],
			[
				179,
				-21
			],
			[
				202,
				28
			]
		],
		"cost": 0.242308,
		"time": 0.022001
	},
	{
		"points": [
			[
				237,
				-70
			],
			[
				200,
				-65
			],
			[
				228,
				-2
			],
			[
				235,
				29
			],
			[
				285,
				72
			],
			[
				35,
				21
			],
			[
				19,
				13
			],
			[
				19,
				-38
			]
		],
		"cost": 0.208858,
		"time": 0.02072
	},
	{
		"points": [
			[
				83,
				-22
			],
			[
				142,
				-44
			],
			[
				156,
				-71
			],
			[
				3,
				-89
			],
			[
				48,
				-72
			],
			[
				322,
				-29
			],
			[
				109,
				60
			],
			[
				113,
				14
			]
		],
		"cost": 0.229835,
		"time": 0.021771
	},
	{
		"points": [
			[
				292,
				-73
			],
			[
				134,
				-57
			],
			[
				244,
				-22
			],
			[
				235,
				28
			],
			[
				252,
				54
			],
			[
				33,
				64
			],
			[
				318,
				-1
			],
			[
				328,
				-11
			]
		],
		"cost": 0.240421,
		"time": 0.021248
	},
	{
		"points": [
			[
				273,
				-61
			],
			[
				238,
				-21
			],
			[
				233,
				17
			],
			[
				78,
				63
			],
			[
				93,
				-10
			],
			[
				12,
				0
			],
			[
				22,
				-39
			],
			[
				167,
				-75
			]
		],
		"cost": 0.265264,
		"time": 0.021152
	},
	{
		"points": [
			[
				44,
				14
			],
			[
				307,
				-39
			],
			[
				281,
				-62
			],
			[
				213,
				-89
			],
			[
				189,
				-54
			],
			[
				149,
				-57
			],
			[
				123,
				57
			],
			[
				95,
				66
			]
		],
		"cost": 0.228391,
		"time": 0.023898
	},
	{
		"points": [
			[
				66,
				3
			],
			[
				40,
				49
			],
			[
				234,
				85
			],
			[
				165,
				-31
			],
			[
				191,
				-25
			],
			[
				200,
				-34
			],
			[
				352,
				-19
			],
			[
				24,
				1
			]
		],
		"cost": 0.250863,
		"time": 0.020358
	},
	{
		"points": [
			[
				39,
				-37
			],
			[
				340,
				-36
			],
			[
				309,
				0
			],
			[
				262,
				-16
			],
			[
				242,
				-81
			],
			[
				68,
				-21
			],
			[
				67,
				2
			],
			[
				41,
				-26
			]
		],
		"cost": 0.198376,
		"time": 0.01971
	},
	{
		"points": [
			[
				253,
				10
			],
			[
				351,
				7
			],
			[
				10,
				6
			],
			[
				38,
				5
			],
			[
				86,
				-16
			],
			[
				31,
				-76
			],
			[
				239,
				-89
			],
			[
				264,
				-2
			]
		],
		"cost": 0.21106,
		"time": 0.02063
	},
	{
		"points": [
			[
				28,
				-41
			],
			[
				332,
				0
			],
			[
				268,
				34
			],
			[
				271,
				13
			],
			[
				265,
				-54
			],
			[
				183,
				-89
			],
			[
				143,
				-66
			],
			[
				53,
				-74
			]
		],
		"cost": 0.19155,
		"time": 0.02119
	},
	{
		"points": [
			[
				189,
				56
			],
			[
				210,
				63
			],
			[
				286,
				71
			],
			[
				271,
				-58
			],
			[
				1,
				-56
			],
			[
				54,
				-33
			],
			[
				105,
				-63
			],
			[
				101,
				-27
			]
		],
		"cost": 0.249703,
		"time": 0.022999
	},
	{
		"points": [
			[
				240,
				-80
			],
			[
				10,
				-41
			],
			[
				11,
				0
			],
			[
				322,
				46
			],
			[
				299,
				54
			],
			[
				35,
				77
			],
			[
				140,
				51
			],
			[
				238,
				-15
			]
		],
		"cost": 0.239537,
		"time": 0.021464
	},
	{
		"points": [
			[
				327,
				0
			],
			[
				330,
				-82
			],
			[
				26,
				-88
			],
			[
				107,
				-42
			],
			[
				199,
				1
			],
			[
				221,
				19
			],
			[
				237,
				0
			],
			[
				266,
				-2
			]
		],
		"cost": 0.206545,
		"time": 0.020865
	},
	{
		"points": [
			[
				358,
				15
			],
			[
				109,
				23
			],
			[
				58,
				-71
			],
			[
				32,
				-67
			],
			[
				227,
				-12
			],
			[
				227,
				15
			],
			[
				233,
				57
			],
			[
				296,
				57
			]
		],
		"cost": 0.265514,
		"time": 0.021314
	},
	{
		"points": [
			[
				232,
				36
			],
			[
				165,
				-45
			],
			[
				354,
				-50
			],
			[
				344,
				-17
			],
			[
				313,
				39
			],
			[
				263,
				85
			],
			[
				179,
				76
			],
			[
				214,
				39
			]
		],
		"cost": 0.222068,
		"time": 0.021709
	},
	{
		"points": [
			[
				246,
				-48
			],
			[
				303,
				-21
			],
			[
				325,
				7
			],
			[
				209,
				82
			],
			[
				189,
				14
			],
			[
				114,
				11
			],
			[
				114,
				-41
			],
			[
				61,
				-40
			]
		],
		"cost": 0.277572,
		"time": 0.020528
	},
	{
		"points": [
			[
				160,
				49
			],
			[
				68,
				18
			],
			[
				172,
				-37
			],
			[
				267,
				-57
			],
			[
				334,
				-23
			],
			[
				290,
				3
			],
			[
				296,
				46
			],
			[
				224,
				69
			]
		],
		"cost": 0.267351,
		"time": 0.020769
	},
	{
		"points": [
			[
				355,
				-49
			],
			[
				193,
				6
			],
			[
				281,
				37
			],
			[
				12,
				81
			],
			[
				47,
				68
			],
			[
				31,
				42
			],
			[
				3,
				-7
			],
			[
				5,
				-30
			]
		],
		"cost": 0.23029,
		"time": 0.020149
	},
	{
		"points": [
			[
				249,
				27
			],
			[
				153,
				2
			],
			[
				151,
				35
			],
			[
				107,
				48
			],
			[
				34,
				57
			],
			[
				8,
				-53
			],
			[
				325,
				-53
			],
			[
				234,
				-40
			]
		],
		"cost": 0.261713,
		"time": 0.020318
	},
	{
		"points": [
			[
				181,
				39
			],
			[
				186,
				58
			],
			[
				101,
				41
			],
			[
				110,
				-14
			],
			[
				143,
				-34
			],
			[
				209,
				-8
			],
			[
				215,
				-9
			],
			[
				259,
				9
			]
		],
		"cost": 0.199272,
		"time": 0.019605
	},
	{
		"points": [
			[
				11,
				61
			],
			[
				68,
				76
			],
			[
				129,
				30
			],
			[
				179,
				58
			],
			[
				227,
				-17
			],
			[
				10,
				-82
			],
			[
				37,
				-15
			],
			[
				20,
				4
			]
		],
		"cost": 0.242868,
		"time": 0.021559
	},
	{
		"points": [
			[
				237,
				8
			],
			[
				253,
				46
			],
			[
				204,
				57
			],
			[
				146,
				17
			],
			[
				86,
				46
			],
			[
				36,
				31
			],
			[
				153,
				-83
			],
			[
				281,
				-7
			]
		],
		"cost": 0.270314,
		"time": 0.021222
	},
	{
		"points": [
			[
				336,
				76
			],
			[
				351,
				77
			],
			[
				8,
				18
			],
			[
				38,
				-47
			],
			[
				326,
				-26
			],
			[
				312,
				-38
			],
			[
				189,
				6
			],
			[
				262,
				85
			]
		],
		"cost": 0.236267,
		"time": 0.021368
	},
	{
		"points": [
			[
				95,
				-88
			],
			[
				13,
				-81
			],
			[
				22,
				-22
			],
			[
				335,
				7
			],
			[
				224,
				68
			],
			[
				180,
				0
			],
			[
				190,
				-21
			],
			[
				173,
				-63
			]
		],
		"cost": 0.211875,
		"time": 0.020909
	},
	{
		"points": [
			[
				116,
				-34
			],
			[
				323,
				-60
			],
			[
				208,
				7
			],
			[
				137,
				27
			],
			[
				161,
				75
			],
			[
				326,
				50
			],
			[
				61,
				15
			],
			[
				69,
				-11
			]
		],
		"cost": 0.290715,
		"time": 0.021289
	},
	{
		"points": [
			[
				281,
				71
			],
			[
				308,
				31
			],
			[
				319,
				-25
			],
			[
				308,
				-57
			],
			[
				84,
				31
			],
			[
				86,
				52
			],
			[
				114,
				73
			],
			[
				177,
				89
			]
		],
		"cost": 0.196541,
		"time": 0.02173
	},
	{
		"points": [
			[
				41,
				-53
			],
			[
				53,
				-48
			],
			[
				51,
				-33
			],
			[
				54,
				9
			],
			[
				206,
				84
			],
			[
				210,
				-4
			],
			[
				321,
				-8
			],
			[
				267,
				-81
			]
		],
		"cost": 0.261774,
		"time": 0.02084
	},
	{
		"points": [
			[
				91,
				-64
			],
			[
				89,
				-49
			],
			[
				166,
				40
			],
			[
				170,
				48
			],
			[
				231,
				69
			],
			[
				330,
				67
			],
			[
				309,
				0
			],
			[
				262,
				-42
			]
		],
		"cost": 0.225734,
		"time": 0.021735
	},
	{
		"points": [
			[
				72,
				89
			],
			[
				352,
				18
			],
			[
				2,
				-5
			],
			[
				75,
				-29
			],
			[
				129,
				-32
			],
			[
				76,
				19
			],
			[
				114,
				30
			],
			[
				177,
				58
			]
		],
		"cost": 0.226,
		"time": 0.020208
	},
	{
		"points": [
			[
				268,
				-58
			],
			[
				2,
				-87
			],
			[
				140,
				-29
			],
			[
				241,
				-3
			],
			[
				244,
				10
			],
			[
				235,
				19
			],
			[
				270,
				59
			],
			[
				348,
				-18
			]
		],
		"cost": 0.24211,
		"time": 0.020556
	},
	{
		"points": [
			[
				330,
				14
			],
			[
				240,
				-60
			],
			[
				233,
				-66
			],
			[
				137,
				21
			],
			[
				211,
				51
			],
			[
				256,
				79
			],
			[
				299,
				59
			],
			[
				10,
				34
			]
		],
		"cost": 0.240793,
		"time": 0.021394
	},
	{
		"points": [
			[
				150,
				3
			],
			[
				325,
				-80
			],
			[
				307,
				-55
			],
			[
				332,
				-38
			],
			[
				305,
				-34
			],
			[
				281,
				77
			],
			[
				182,
				89
			],
			[
				163,
				23
			]
		],
		"cost": 0.21642,
		"time": 0.022987
	},
	{
		"points": [
			[
				269,
				62
			],
			[
				264,
				79
			],
			[
				74,
				87
			],
			[
				178,
				47
			],
			[
				199,
				20
			],
			[
				141,
				-50
			],
			[
				311,
				-56
			],
			[
				348,
				-37
			]
		],
		"cost": 0.230938,
		"time": 0.022156
	},
	{
		"points": [
			[
				242,
				-75
			],
			[
				209,
				-43
			],
			[
				159,
				-18
			],
			[
				158,
				-6
			],
			[
				281,
				73
			],
			[
				319,
				31
			],
			[
				344,
				-21
			],
			[
				355,
				-57
			]
		],
		"cost": 0.212528,
		"time": 0.020885
	},
	{
		"points": [
			[
				308,
				79
			],
			[
				52,
				88
			],
			[
				187,
				81
			],
			[
				112,
				-9
			],
			[
				146,
				-83
			],
			[
				18,
				-2
			],
			[
				45,
				15
			],
			[
				297,
				67
			]
		],
		"cost": 0.229623,
		"time": 0.021812
	},
	{
		"points": [
			[
				327,
				50
			],
			[
				45,
				36
			],
			[
				92,
				58
			],
			[
				168,
				-18
			],
			[
				194,
				-61
			],
			[
				35,
				-72
			],
			[
				285,
				-49
			],
			[
				298,
				54
			]
		],
		"cost": 0.253427,
		"time": 0.022669
	},
	{
		"points": [
			[
				81,
				-29
			],
			[
				137,
				-54
			],
			[
				53,
				-83
			],
			[
				345,
				33
			],
			[
				135,
				84
			],
			[
				235,
				47
			],
			[
				169,
				9
			],
			[
				120,
				1
			]
		],
		"cost": 0.263441,
		"time": 0.021528
	},
	{
		"points": [
			[
				354,
				20
			],
			[
				60,
				-35
			],
			[
				76,
				-46
			],
			[
				129,
				-39
			],
			[
				150,
				-21
			],
			[
				237,
				-54
			],
			[
				304,
				36
			],
			[
				26,
				61
			]
		],
		"cost": 0.246879,
		"time": 0.021933
	},
	{
		"points": [
			[
				262,
				16
			],
			[
				305,
				-39
			],
			[
				305,
				-65
			],
			[
				88,
				-74
			],
			[
				119,
				-77
			],
			[
				203,
				-5
			],
			[
				202,
				68
			],
			[
				291,
				89
			]
		],
		"cost": 0.218404,
		"time": 0.02148
	},
	{
		"points": [
			[
				249,
				-85
			],
			[
				2,
				-45
			],
			[
				342,
				18
			],
			[
				24,
				72
			],
			[
				145,
				53
			],
			[
				57,
				30
			],
			[
				35,
				11
			],
			[
				72,
				6
			]
		],
		"cost": 0.250803,
		"time": 0.020915
	},
	{
		"points": [
			[
				146,
				-19
			],
			[
				97,
				52
			],
			[
				210,
				63
			],
			[
				266,
				59
			],
			[
				202,
				0
			],
			[
				278,
				-58
			],
			[
				157,
				-86
			],
			[
				124,
				-29
			]
		],
		"cost": 0.242697,
		"time": 0.021874
	},
	{
		"points": [
			[
				198,
				12
			],
			[
				225,
				-16
			],
			[
				170,
				-18
			],
			[
				134,
				-68
			],
			[
				254,
				-89
			],
			[
				55,
				-70
			],
			[
				83,
				41
			],
			[
				62,
				74
			]
		],
		"cost": 0.236931,
		"time": 0.021384
	},
	{
		"points": [
			[
				189,
				25
			],
			[
				211,
				36
			],
			[
				224,
				77
			],
			[
				319,
				71
			],
			[
				44,
				75
			],
			[
				105,
				40
			],
			[
				170,
				-37
			],
			[
				283,
				-39
			]
		],
		"cost": 0.245629,
		"time": 0.021009
	},
	{
		"points": [
			[
				218,
				61
			],
			[
				278,
				18
			],
			[
				207,
				-57
			],
			[
				261,
				-81
			],
			[
				301,
				-60
			],
			[
				0,
				-40
			],
			[
				17,
				-63
			],
			[
				100,
				4
			]
		],
		"cost": 0.257556,
		"time": 0.021937
	},
	{
		"points": [
			[
				264,
				-34
			],
			[
				330,
				56
			],
			[
				317,
				83
			],
			[
				358,
				89
			],
			[
				44,
				65
			],
			[
				30,
				29
			],
			[
				71,
				34
			],
			[
				148,
				-22
			]
		],
		"cost": 0.236298,
		"time": 0.021983
	},
	{
		"points": [
			[
				262,
				27
			],
			[
				210,
				6
			],
			[
				48,
				53
			],
			[
				93,
				-25
			],
			[
				241,
				-82
			],
			[
				278,
				-65
			],
			[
				293,
				-31
			],
			[
				287,
				16
			]
		],
		"cost": 0.255123,
		"time": 0.02663
	},
	{
		"points": [
			[
				317,
				-86
			],
			[
				164,
				-84
			],
			[
				123,
				-83
			],
			[
				58,
				-40
			],
			[
				189,
				79
			],
			[
				188,
				-43
			],
			[
				259,
				-41
			],
			[
				263,
				-54
			]
		],
		"cost": 0.23254,
		"time": 0.021536
	},
	{
		"points": [
			[
				160,
				-16
			],
			[
				244,
				77
			],
			[
				49,
				-20
			],
			[
				161,
				-86
			],
			[
				253,
				-68
			],
			[
				246,
				-56
			],
			[
				265,
				-40
			],
			[
				236,
				-40
			]
		],
		"cost": 0.247105,
		"time": 0.02132
	},
	{
		"points": [
			[
				45,
				44
			],
			[
				8,
				60
			],
			[
				224,
				61
			],
			[
				282,
				35
			],
			[
				239,
				-26
			],
			[
				161,
				-83
			],
			[
				138,
				21
			],
			[
				74,
				5
			]
		],
		"cost": 0.266039,
		"time": 0.020763
	},
	{
		"points": [
			[
				135,
				45
			],
			[
				129,
				45
			],
			[
				332,
				43
			],
			[
				30,
				-18
			],
			[
				244,
				-73
			],
			[
				130,
				-76
			],
			[
				93,
				-35
			],
			[
				142,
				-12
			]
		],
		"cost": 0.243666,
		"time": 0.020309
	},
	{
		"points": [
			[
				9,
				-38
			],
			[
				309,
				50
			],
			[
				205,
				22
			],
			[
				250,
				83
			],
			[
				342,
				89
			],
			[
				48,
				86
			],
			[
				26,
				60
			],
			[
				46,
				-15
			]
		],
		"cost": 0.222949,
		"time": 0.021742
	},
	{
		"points": [
			[
				64,
				-28
			],
			[
				355,
				-41
			],
			[
				334,
				-58
			],
			[
				300,
				-87
			],
			[
				278,
				-45
			],
			[
				256,
				57
			],
			[
				224,
				62
			],
			[
				164,
				-28
			]
		],
		"cost": 0.254317,
		"time": 0.021428
	},
	{
		"points": [
			[
				77,
				-19
			],
			[
				136,
				-35
			],
			[
				48,
				-81
			],
			[
				274,
				-50
			],
			[
				284,
				10
			],
			[
				275,
				76
			],
			[
				46,
				-4
			],
			[
				59,
				-36
			]
		],
		"cost": 0.246249,
		"time": 0.021948
	},
	{
		"points": [
			[
				98,
				57
			],
			[
				78,
				-30
			],
			[
				75,
				-36
			],
			[
				69,
				-72
			],
			[
				245,
				-80
			],
			[
				171,
				-27
			],
			[
				198,
				7
			],
			[
				267,
				59
			]
		],
		"cost": 0.222097,
		"time": 0.021023
	},
	{
		"points": [
			[
				320,
				-45
			],
			[
				272,
				1
			],
			[
				206,
				24
			],
			[
				166,
				76
			],
			[
				145,
				72
			],
			[
				351,
				38
			],
			[
				53,
				-40
			],
			[
				139,
				-89
			]
		],
		"cost": 0.252134,
		"time": 0.021224
	},
	{
		"points": [
			[
				210,
				-49
			],
			[
				285,
				26
			],
			[
				294,
				36
			],
			[
				257,
				79
			],
			[
				144,
				66
			],
			[
				338,
				50
			],
			[
				354,
				-8
			],
			[
				151,
				-55
			]
		],
		"cost": 0.256322,
		"time": 0.02238
	},
	{
		"points": [
			[
				272,
				-48
			],
			[
				299,
				-17
			],
			[
				296,
				-59
			],
			[
				14,
				-64
			],
			[
				38,
				-3
			],
			[
				51,
				71
			],
			[
				44,
				75
			],
			[
				161,
				-6
			]
		],
		"cost": 0.255311,
		"time": 0.021493
	},
	{
		"points": [
			[
				342,
				-7
			],
			[
				272,
				64
			],
			[
				13,
				76
			],
			[
				125,
				55
			],
			[
				168,
				-52
			],
			[
				228,
				-79
			],
			[
				270,
				-76
			],
			[
				45,
				-85
			]
		],
		"cost": 0.230986,
		"time": 0.023495
	},
	{
		"points": [
			[
				274,
				56
			],
			[
				174,
				69
			],
			[
				195,
				0
			],
			[
				118,
				-16
			],
			[
				241,
				-79
			],
			[
				316,
				-73
			],
			[
				278,
				-27
			],
			[
				321,
				16
			]
		],
		"cost": 0.25096,
		"time": 0.021889
	},
	{
		"points": [
			[
				69,
				-61
			],
			[
				55,
				-58
			],
			[
				332,
				36
			],
			[
				198,
				50
			],
			[
				148,
				-57
			],
			[
				146,
				-67
			],
			[
				160,
				-87
			],
			[
				111,
				-78
			]
		],
		"cost": 0.214269,
		"time": 0.022622
	},
	{
		"points": [
			[
				61,
				-30
			],
			[
				49,
				4
			],
			[
				104,
				28
			],
			[
				238,
				87
			],
			[
				309,
				72
			],
			[
				236,
				50
			],
			[
				247,
				14
			],
			[
				195,
				-10
			]
		],
		"cost": 0.237328,
		"time": 0.021236
	},
	{
		"points": [
			[
				130,
				14
			],
			[
				219,
				-3
			],
			[
				313,
				-13
			],
			[
				339,
				55
			],
			[
				112,
				85
			],
			[
				191,
				71
			],
			[
				193,
				58
			],
			[
				154,
				44
			]
		],
		"cost": 0.215957,
		"time": 0.021821
	},
	{
		"points": [
			[
				59,
				-29
			],
			[
				20,
				-55
			],
			[
				283,
				-71
			],
			[
				314,
				5
			],
			[
				316,
				6
			],
			[
				16,
				84
			],
			[
				140,
				69
			],
			[
				14,
				1
			]
		],
		"cost": 0.233215,
		"time": 0.020663
	},
	{
		"points": [
			[
				201,
				17
			],
			[
				41,
				86
			],
			[
				290,
				44
			],
			[
				287,
				31
			],
			[
				1,
				-28
			],
			[
				25,
				-66
			],
			[
				161,
				-50
			],
			[
				200,
				-4
			]
		],
		"cost": 0.226102,
		"time": 0.020355
	}
]